dataprocxy/__init__.py
dataprocxy/dataprocxy.py
dataprocxy-0.4.data/scripts/dataprocxy
dataprocxy-0.4.dist-info/DESCRIPTION.rst
dataprocxy-0.4.dist-info/METADATA
dataprocxy-0.4.dist-info/RECORD
dataprocxy-0.4.dist-info/WHEEL
dataprocxy-0.4.dist-info/metadata.json
dataprocxy-0.4.dist-info/top_level.txt
