Metadata-Version: 2.0
Name: dataprocxy
Version: 0.4
Summary: using a dataproc job or cluster id and a project, open a browser to important URLs using an ssh SOCKS proxy
Home-page: https://github.com/spotify/dataprocxy
Author: Twan Wolthof
Author-email: xeago@spotify.com
License: Apache 2.0
Platform: UNKNOWN
Requires-Dist: google-api-python-client
